cosine/__init__.py
cosine/config.yaml.example
cosine/core/__init__.py
cosine/core/algo.py
cosine/core/args.py
cosine/core/config.py
cosine/core/context.py
cosine/core/instrument.py
cosine/core/logger.py
cosine/core/order_worker.py
cosine/core/order_worker_types.py
cosine/core/proc_workers.py
cosine/core/tradeable.py
cosine/core/utils.py
cosine/pricing/__init__.py
cosine/pricing/base_feed.py
cosine/pricing/cryptocompare.py
cosine/pricing/pricers/__init__.py
cosine/pricing/pricers/base_pricer.py
cosine/pricing/pricers/nullpricer.py
cosine/strategies/__init__.py
cosine/strategies/base_strategy.py
cosine/strategies/multi_strategy.py
cosine/strategies/noddy_floater.py
cosine/venues/__init__.py
cosine/venues/base_venue.py
cosine/venues/bem/__init__.py
cosine/venues/bem/bem.py
cosine/venues/bem/types.py
cosine/venues/bem/worker.py
cosine_crypto-0.2.50.dist-info/METADATA
cosine_crypto-0.2.50.dist-info/RECORD
cosine_crypto-0.2.50.dist-info/WHEEL
cosine_crypto-0.2.50.dist-info/top_level.txt
